jsonmask/__init__.py
jsonmask/mask.py
jsonmask/parsing.py
jsonmask/tests/__init__.py
jsonmask/tests/conftest.py
jsonmask/tests/test_mask.py
jsonmask/tests/test_parsing.py
jsonmask-0.1.1.dist-info/WHEEL
jsonmask-0.1.1.dist-info/METADATA
jsonmask-0.1.1.dist-info/RECORD
