Metadata-Version: 2.1
Name: jsonmask
Version: 0.1.1
Summary: Implements the Google Partial Response protocol in Python
Home-page: https://github.com/zapier/jsonmask
License: MIT
Keywords: jsonmask,json,google partial response
Author: Craig Labenz
Author-email: craig.labenz@gmail.com
Requires-Python: >=2.7, !=3.0.*, !=3.1.*, !=3.2.*, !=3.3.*, !=3.4.*, !=3.5.*
Classifier: Development Status :: 1 - Planning
Classifier: License :: OSI Approved :: MIT License
Classifier: Natural Language :: English
Classifier: Operating System :: OS Independent
Classifier: Programming Language :: Python
Classifier: Programming Language :: Python :: 2
Classifier: Programming Language :: Python :: 2.7
Classifier: Programming Language :: Python :: 3
Classifier: Programming Language :: Python :: 3.6
Classifier: Programming Language :: Python :: 3.7
Project-URL: Documentation, https://github.com/zapier/jsonmask/blob/master/README.md
Project-URL: Repository, https://github.com/zapier/jsonmask
